pyqttoast/__init__.py
pyqttoast/constants.py
pyqttoast/drop_shadow.py
pyqttoast/icon_utils.py
pyqttoast/toast.py
pyqttoast/toast_enums.py
pyqttoast/utils.py
pyqttoast/css/drop_shadow.css
pyqttoast/css/toast.css
pyqttoast/hooks/__init__.py
pyqttoast/hooks/hook-pyqttoast.py
pyqttoast/icons/close.png
pyqttoast/icons/error.png
pyqttoast/icons/information.png
pyqttoast/icons/success.png
pyqttoast/icons/warning.png
pyqt_toast_notification-1.3.3.dist-info/LICENSE
pyqt_toast_notification-1.3.3.dist-info/METADATA
pyqt_toast_notification-1.3.3.dist-info/WHEEL
pyqt_toast_notification-1.3.3.dist-info/entry_points.txt
pyqt_toast_notification-1.3.3.dist-info/top_level.txt
pyqt_toast_notification-1.3.3.dist-info/RECORD
