Metadata-Version: 2.1
Name: pyqt-toast-notification
Version: 1.3.3
Summary: A fully customizable toast notification library for PyQt and PySide
Home-page: https://github.com/niklashenning/pyqttoast
Author: Niklas Henning
Author-email: business@niklashenning.com
License: MIT
Keywords: python,pyqt,qt,toast,notification
Classifier: Programming Language :: Python :: 3
Classifier: Operating System :: OS Independent
Classifier: License :: OSI Approved :: MIT License
Requires-Python: >=3.7
License-File: LICENSE
Requires-Dist: QtPy >=2.4.1
